isinstance2.py
isinstance2-0.1.8.dist-info/LICENSE
isinstance2-0.1.8.dist-info/WHEEL
isinstance2-0.1.8.dist-info/METADATA
isinstance2-0.1.8.dist-info/RECORD
