Metadata-Version: 2.1
Name: isinstance2
Version: 0.1.8
Summary: 
Author: IsaacBreen
Author-email: mail@isaacbreen.com
Requires-Python: >=3.11,<4.0
Classifier: Programming Language :: Python :: 3
Classifier: Programming Language :: Python :: 3.11
